imageaug/__init__.py
imageaug/functional.py
imageaug/transforms.py
ImageAug-0.1.0.post0.dist-info/LICENSE
ImageAug-0.1.0.post0.dist-info/METADATA
ImageAug-0.1.0.post0.dist-info/WHEEL
ImageAug-0.1.0.post0.dist-info/top_level.txt
ImageAug-0.1.0.post0.dist-info/RECORD
