Metadata-Version: 2.1
Name: ImageAug
Version: 0.1.0.post0
Summary: Image augmentation for PyTorch
Home-page: https://github.com/paixi/ImageAug
Author: Paixi
Author-email: paixi@protonmail.com
License: UNKNOWN
Platform: UNKNOWN
Classifier: Programming Language :: Python
Classifier: Programming Language :: Python :: 3
Classifier: License :: OSI Approved :: MIT License
Classifier: Topic :: Scientific/Engineering :: Artificial Intelligence
Classifier: Topic :: Scientific/Engineering :: Image Recognition
